discordlabs/__init__.py
discordlabs/client.py
discordlabs.py-0.0.6.dist-info/METADATA
discordlabs.py-0.0.6.dist-info/WHEEL
discordlabs.py-0.0.6.dist-info/top_level.txt
discordlabs.py-0.0.6.dist-info/RECORD
