Metadata-Version: 2.1
Name: discordlabs.py
Version: 0.0.6
Summary: A simple API wrapper for Discord Labs.
Home-page: https://github.com/discordbotcord/Python-Library
Author: Anish Anne
License: UNKNOWN
Project-URL: Support, https://discord.gg/SMpSzuX
Project-URL: Source, https://github.com/discordbotcord/Python-Library
Keywords: api wrapper discord bot bots botlist labs discordlabs discordbotlabs
Platform: UNKNOWN
Classifier: License :: OSI Approved :: MIT License
Classifier: Programming Language :: Python :: 3
Classifier: Natural Language :: English
Classifier: Intended Audience :: Developers
Classifier: Operating System :: OS Independent
Requires-Python: >= 3.5
Requires-Dist: aiohttp
Requires-Dist: requests
